Workbook

Sheet 📋 Instructions
B1: TFSA / RRSP / FHSA TRACKER
B2: Track • Plan • Grow Your Wealth with AI-Powered Insights
B3: Her Money & AI | AI-Powered Finance Education | hermoneyandai.ca
B5: "You educate a man; you educate a man. You educate a woman; you educate a generation."
B7: — Her Money & AI Mission
B9: ABOUT THIS TEMPLATE
B10: Track your Canadian registered accounts in one place. Enter your contribution room from CRA My Account, your balances, and contributions to see remaining room, projected growth, and tax savings at a glance.
B12: WHAT'S IN THIS FILE
B13: Sheet Name | C13: Purpose | D13: How to Use | E13: Notes
B14: 📋 Instructions | C14: Welcome & how-to | D14: Read first | E14: You are here
B15: 💰 TFSA Tracker | C15: Tax-Free Savings Account | D15: Enter room & contributions | E15: 2025 limit: $7,000
B16: 🏠 FHSA Tracker | C16: First Home Savings Account | D16: Enter contributions & goal | E16: Annual: $8,000 | Lifetime: $40,000
B17: 🏦 RRSP Tracker | C17: Registered Retirement Savings | D17: Enter income & contributions | E17: 2025 max: $32,490
B18: 📊 Summary | C18: All-accounts dashboard | D18: Auto-calculates | E18: Read-only
B19: 🍁 Canada Tips | C19: Key rules & 2025 limits | D19: Reference sheet | E19: Always verify with CRA
B21: COLOUR CODING GUIDE
B22: 🔵 Blue text | C22: Input cells — these are for YOU to fill in
B23: ⚫ Dark text | C23: Calculated formulas — do not edit these
B24: 🟡 Gold/Yellow background | C24: EDUCATIONAL USE DISCLAIMER section
B25: 🟢 Green/Teal header | C25: Section groupings for easy navigation
B27: 💡 AI TIPS — USE THESE PROMPTS WITH CHATGPT OR CLAUDE
B28: "I have $[X] TFSA room and $[Y] RRSP room. I can invest $[Z]. How should I split it for maximum tax efficiency?"
B29: "Explain the FHSA to me — who qualifies, what are the limits, and how do I use it to buy my first home in Canada?"
B30: "I earn $[X]/year in [province]. Should I prioritize RRSP or TFSA contributions this year? My marginal tax rate is approximately [Z]%."
B31: "What happens to my FHSA if I don't buy a home within 15 years? What are my options?"
B33: EDUCATIONAL USE DISCLAIMER
B34: ⚠️ DISCLAIMER: This template is for educational and informational purposes only.
B35: It does not constitute personalized financial, investment, tax, or legal advice.
B36: Consult a registered financial advisor for advice specific to your situation.
B37: © Her Money & AI | AI-Powered Finance Education | hermoneyandai.ca

Sheet 💰 TFSA Tracker
B1: TFSA TRACKER
B2: Tax-Free Savings Account — 2025 Annual Limit: $7,000
B4: CONTRIBUTION ROOM CALCULATOR
B5: Description | C5: Your Amount | D5: Notes
B6: 2025 Annual Contribution Limit | C6: 0 | D6: Fixed at $7,000 for 2025
B7: Carry-Forward Room (prior years) | C7: 0 | D7: Check CRA My Account
B8: Total Available Room | C8: =C6+C7 -> 0 | D8: Calculated automatically
B9: YTD Contributions Made (2025) | C9: 0 | D9: What you've contributed so far
B10: Remaining Contribution Room | C10: =C8-C9 -> 0 | D10: Do not over-contribute — 1% penalty/month
B12: BALANCE & GROWTH TRACKER
B13: Account / Investment | C13: Current Balance | D13: Prior Year Balance | E13: Growth ($)
B14: TFSA – Savings Account | E14: =C14-D14 -> 0
B15: TFSA – GIC / Term Deposit | E15: =C15-D15 -> 0
B16: TFSA – ETFs / Index Funds | E16: =C16-D16 -> 0
B17: TFSA – Stocks | E17: =C17-D17 -> 0
B18: TFSA – Mutual Funds | E18: =C18-D18 -> 0
B19: Other TFSA Holdings | E19: =C19-D19 -> 0
B20: TOTAL TFSA BALANCE | C20: =SUM(C14:C19) -> 0 | D20: =SUM(D14:D19) -> 0 | E20: =C20-D20 -> 0
B22: 📌 Withdrawals from your TFSA are added back to your contribution room on January 1 of the following year.
B23: 📌 Over-contributing to your TFSA triggers a 1% penalty per month on the excess. Always verify room with CRA My Account.
B25: EDUCATIONAL USE DISCLAIMER
B26: ⚠️ DISCLAIMER: This template is for educational and informational purposes only.
B27: It does not constitute personalized financial, investment, tax, or legal advice.
B28: Consult a registered financial advisor for advice specific to your situation.
B29: © Her Money & AI | AI-Powered Finance Education | hermoneyandai.ca

Sheet 🏠 FHSA Tracker
B1: FHSA TRACKER
B2: First Home Savings Account — Annual: $8,000 | Lifetime: $40,000
B4: CONTRIBUTION ROOM & LIMITS
B5: Description | C5: Your Amount | D5: Notes
B6: Annual Contribution Limit | C6: 0 | D6: $8,000 per year
B7: Lifetime Contribution Limit | C7: 0 | D7: $40,000 lifetime maximum
B8: YTD Contributions Made (2025) | C8: 0 | D8: Enter what you've contributed
B9: Remaining Annual Room | C9: =C6-C8 -> 0 | D9: Calculated
B10: Carry-Forward Unused Room (max $8,000) | C10: =MIN(C6-C8,8000) -> 0 | D10: Unused prior year room, max $8k
B11: Total Cumulative Contributions | C11: 0 | D11: All years combined — must not exceed $40,000
B12: Remaining Lifetime Room | C12: =C7-C11 -> 0 | D12: Calculated
B15: HOME PURCHASE GOAL PLANNER
B16: Field | C16: Your Input | D16: Notes
B17: Target Home Purchase Year | C17: 0 | D17: e.g. 2028
B18: Years Until Purchase | C18: =C17-YEAR(TODAY()) -> -2026 | D18: Calculated
B19: Current FHSA Balance | C19: 0 | D19: Your current balance
B20: Expected Annual Contribution | C20: 0 | D20: How much you plan to add per year
B21: Expected Annual Return | C21: 0 | D21: e.g. 0.05 for 5%
B22: Projected Balance at Purchase | C22: =IFERROR(C19*(1+C21)^C18+C20*((1+C21)^C18-1)/C21,C19+C20*C18) -> 0 | D22: Estimate — assumes constant return
B23: Est. Tax Deduction This Year | C23: =C20*0.33 -> 0 | D23: Rough estimate at ~33% marginal rate
B26: 📌 FHSA: contributions ARE tax-deductible AND qualifying first-home withdrawals are 100% tax-free. Best of both worlds!
B28: EDUCATIONAL USE DISCLAIMER
B29: ⚠️ DISCLAIMER: This template is for educational and informational purposes only.
B30: It does not constitute personalized financial, investment, tax, or legal advice.
B31: Consult a registered financial advisor for advice specific to your situation.
B32: © Her Money & AI | AI-Powered Finance Education | hermoneyandai.ca

Sheet 🏦 RRSP Tracker
B1: RRSP TRACKER
B2: Registered Retirement Savings Plan — 2025 Max: $32,490
B4: CONTRIBUTION ROOM CALCULATOR
B5: Description | C5: Your Amount | D5: Notes
B6: Prior Year Net Earned Income | C6: 0 | D6: From your prior year NOA (Notice of Assessment)
B7: 2025 RRSP Limit (18% of earned income) | C7: =MIN(C6*0.18,32490) -> 0 | D7: Maximum $32,490 for 2025
B8: Carry-Forward Room (from prior years) | C8: 0 | D8: From your CRA My Account / NOA
B9: Total Available RRSP Room | C9: =C7+C8 -> 0 | D9: Calculated
B10: YTD Contributions Made (2025) | C10: 0 | D10: What you've contributed this year
B11: Remaining RRSP Room | C11: =C9-C10 -> 0 | D11: Calculated
B12: Current RRSP Balance | C12: 0 | D12: Your current account balance
B13: Estimated Tax Refund on Contributions | C13: =C10*0.33 -> 0 | D13: Rough ~33% marginal — adjust to your bracket
B16: RETIREMENT PROJECTION
B17: Field | C17: Your Input | D17: Notes
B18: Current Age | C18: 0 | D18: Your age today
B19: Target Retirement Age | C19: 0 | D19: When you want to retire (RRIF at 71)
B20: Years to Retirement | C20: =C19-C18 -> 0 | D20: Calculated
B21: Annual Contribution | C21: 0 | D21: How much you plan to add per year
B22: Expected Annual Return | C22: 0 | D22: e.g. 0.07 for 7%
B23: Projected RRSP at Retirement | C23: =IFERROR(C13*(1+C22)^C20+C21*((1+C22)^C20-1)/C22,C13+C21*C20) -> 0 | D23: Estimate only
B26: 📌 RRSP contributions reduce your taxable income. Deadline is 60 days after December 31. Converts to RRIF at age 71.
B28: EDUCATIONAL USE DISCLAIMER
B29: ⚠️ DISCLAIMER: This template is for educational and informational purposes only.
B30: It does not constitute personalized financial, investment, tax, or legal advice.
B31: Consult a registered financial advisor for advice specific to your situation.
B32: © Her Money & AI | AI-Powered Finance Education | hermoneyandai.ca

Sheet 📊 Summary
B1: REGISTERED ACCOUNTS SUMMARY
B2: All accounts at a glance — auto-calculated
B4: CONTRIBUTION ROOM SUMMARY
B5: Account | C5: Annual Limit | D5: Available Room | E5: Used This Year | F5: Remaining
B6: 💰 TFSA | C6: $7,000 | D6: ='💰 TFSA Tracker'!C8 -> 0 | E6: ='💰 TFSA Tracker'!C9 -> 0 | F6: ='💰 TFSA Tracker'!C10 -> 0
B7: 🏠 FHSA | C7: $8,000 | D7: ='🏠 FHSA Tracker'!C9 -> 0 | E7: ='🏠 FHSA Tracker'!C8 -> 0 | F7: ='🏠 FHSA Tracker'!C9 -> 0
B8: 🏦 RRSP | C8: $32,490 | D8: ='🏦 RRSP Tracker'!C9 -> 0 | E8: ='🏦 RRSP Tracker'!C10 -> 0 | F8: ='🏦 RRSP Tracker'!C11 -> 0
B10: KPI CARDS — YOUR MONEY AT A GLANCE
C11: TFSA Balance | D11: RRSP Balance | E11: FHSA Balance | F11: Total Invested
C12: ='💰 TFSA Tracker'!C20 -> 0 | D12: ='🏦 RRSP Tracker'!C13 -> 0 | E12: ='🏠 FHSA Tracker'!C19 -> 0 | F12: ='💰 TFSA Tracker'!C20+'🏦 RRSP Tracker'!C13+'🏠 FHSA Tracker'!C19 -> 0
B14: EDUCATIONAL USE DISCLAIMER
B15: ⚠️ DISCLAIMER: This template is for educational and informational purposes only.
B16: It does not constitute personalized financial, investment, tax, or legal advice.
B17: Consult a registered financial advisor for advice specific to your situation.
B18: © Her Money & AI | AI-Powered Finance Education | hermoneyandai.ca

Sheet 🍁 Canada Tips
B1: CANADIAN REGISTERED ACCOUNTS — QUICK REFERENCE
B2: 2025 Limits & Key Rules for Canadian Residents
B4: 💰 TFSA – Tax-Free Savings Account
B5: • 2025 annual limit: $7,000
B6: • Contributions not tax-deductible; growth and withdrawals are 100% tax-free.
B7: • Withdrawn amounts are re-added to your room the following January 1.
B8: • Anyone 18+ who is a Canadian resident can contribute. SIN required.
B9: • Total cumulative room since 2009 (if eligible at 18): $95,000 as of 2025.
B12: 🏠 FHSA – First Home Savings Account
B13: • Annual limit: $8,000 | Lifetime limit: $40,000
B14: • For first-time home buyers only. Must be opened and used within 15 years.
B15: • Contributions ARE tax-deductible (like RRSP) AND qualifying withdrawals are tax-free (like TFSA).
... B39: © Her Money & AI | AI-Powered Finance Education | hermoneyandai.ca
