Workbook

Sheet 📋 Instructions
B1: FIRE TRACKER
B2: Track • Plan • Grow Your Wealth with AI-Powered Insights
B3: Her Money & AI | AI-Powered Finance Education | hermoneyandai.ca
B5: "You educate a man; you educate a man. You educate a woman; you educate a generation."
B7: — Her Money & AI Mission
B9: ABOUT THIS TEMPLATE
B10: Calculate your Financial Independence, Retire Early (FIRE) number, track your progress, and see exactly how many years until you reach financial freedom. Enter your numbers and watch your FIRE date appear.
B12: WHAT'S IN THIS FILE
B13: Sheet Name | C13: Purpose | D13: How to Use | E13: Notes
B14: 📋 Instructions | C14: Welcome & how-to | D14: Read first | E14: You are here
B15: 🔢 Your FIRE Number | C15: Calculate FI target | D15: Enter expenses & SWR | E15: 25x rule + more
B16: 📈 Progress Tracker | C16: Track progress to FI | D16: Enter net worth & savings | E16: Auto-calculates
B17: 📅 Timeline | C17: Year-by-year projection | D17: Auto-fills from inputs | E17: Read-only
B18: 🍁 Canada Tips | C18: Canadian FIRE strategy | D18: Reference guide | E18: Tax tips included
B20: COLOUR CODING GUIDE
B21: 🔵 Blue text | C21: Input cells — these are for YOU to fill in
B22: ⚫ Dark text | C22: Calculated formulas — do not edit these
B23: 🟡 Gold/Yellow background | C23: EDUCATIONAL USE DISCLAIMER section
B24: 🟢 Green/Teal header | C24: Section groupings for easy navigation
B26: 💡 AI TIPS — USE THESE PROMPTS WITH CHATGPT OR CLAUDE
B27: "I am [age], earn $[X]/year, spend $[Y]/year in Canada. What is my FIRE number and realistic timeline?"
B28: "What are the differences between Lean FIRE, Regular FIRE, and Fat FIRE for a family of [X] in [city], Canada?"
B29: "What Canadian tax strategies should I know to reach financial independence faster?"
B30: "I want to retire at [age] in Canada. How much do I need in my TFSA vs RRSP vs non-registered accounts?"
B32: EDUCATIONAL USE DISCLAIMER
B33: ⚠️ DISCLAIMER: This template is for educational and informational purposes only.
B34: It does not constitute personalized financial, investment, tax, or legal advice.
B35: Consult a registered financial advisor for advice specific to your situation.
B36: © Her Money & AI | AI-Powered Finance Education | hermoneyandai.ca

Sheet 🔢 Your FIRE Number
B1: YOUR FIRE NUMBER
B2: How much do you need to be financially free?
B4: STEP 1 — YOUR EXPENSES
B5: Description | C5: Amount | D5: Notes
B6: Current Annual Expenses | C6: 0 | D6: All living expenses — honest total
B7: Expected Retirement Annual Expenses | C7: 0 | D7: Often 70-80% of current; enter your estimate
B8: Inflation Adjustment (annual %) | C8: 0 | D8: e.g. 0.02 for 2%
B9: Kids / Dependents Additional Cost | C9: 0 | D9: Extra annual costs for family
B10: Total Retirement Annual Need | C10: =C7+C9 -> 0 | D10: Calculated
B13: STEP 2 — YOUR FIRE NUMBER (CHOOSE YOUR STYLE)
B14: FIRE Style | C14: Your Number | D14: Multiplier | E14: What it means
B15: 🌿 Lean FIRE | C15: =C10*20 -> 0 | D15: 20x | E15: Frugal lifestyle — bare essentials covered
B16: 🔥 Regular FIRE | C16: =C10*25 -> 0 | D16: 25x | E16: Standard 4% rule — most common target
B17: 💎 Fat FIRE | C17: =C10*30 -> 0 | D17: 30x | E17: Comfortable lifestyle — travel, extras
B18: 🍁 Conservative FIRE | C18: =C10*33 -> 0 | D18: 33x | E18: 3% SWR — extra buffer for Canadian longevity
B21: STEP 3 — YOUR PERSONAL TARGET
B22: Description | C22: Your Amount | D22: Notes
B23: My Chosen FIRE Target | C23: 0 | D23: Copy from above — or enter your own
B24: Safe Withdrawal Rate (SWR) | C24: 0 | D24: e.g. 0.04 for 4% — common starting point
B25: Annual Withdrawal Allowed | C25: =C23*C24 -> 0 | D25: Calculated — your retirement income
B28: EDUCATIONAL USE DISCLAIMER
B29: ⚠️ DISCLAIMER: This template is for educational and informational purposes only.
B30: It does not constitute personalized financial, investment, tax, or legal advice.
B31: Consult a registered financial advisor for advice specific to your situation.
B32: © Her Money & AI | AI-Powered Finance Education | hermoneyandai.ca

Sheet 📈 Progress Tracker
B1: FIRE PROGRESS TRACKER
B2: How close are you to financial independence?
B4: YOUR CURRENT POSITION
B5: Field | C5: Your Input | D5: Notes
B6: Current Age | C6: 0
B7: Target FIRE Age | C7: 0 | D7: When you want to be financially free
B8: Years Remaining to FIRE | C8: =C7-C6 -> 0 | D8: Calculated
B9: My Chosen FIRE Target ($) | C9: 0 | D9: Enter from FIRE Number sheet
B10: Current Invested Assets (Total) | C10: 0 | D10: TFSA + RRSP + FHSA + non-reg + other
B11: FIRE Progress | C11: =IFERROR(C10/C9,0) -> 0 | D11: Calculated — % of target reached
B12: Monthly Savings / Investing | C12: 0
B13: Annual Savings Amount | C13: =C12*12 -> 0 | D13: Calculated
B14: Expected Annual Return | C14: 0 | D14: e.g. 0.07 for 7%
B15: Projected FIRE Date | C15: =IFERROR(DATE(YEAR(TODAY())+ROUND(IFERROR(NPER(C14/12,-C12,C10,C9*-1),C8),0),MONTH(TODAY()),1),"Enter inputs") -> 46082 | D15: Estimate — assumes steady contributions & return
B18: FIRE PROGRESS DASHBOARD
B19: FIRE Target | C19: Current Assets | D19: Progress | E19: Years Left
B20: =C9 -> 0 | C20: =C10 -> 0 | D20: =IFERROR(C10/C9,0) -> 0 | E20: =IFERROR(ROUND(NPER(C14/12,-C12,C10,C9*-1)/12,1),C8-C6) -> 0
B22: EDUCATIONAL USE DISCLAIMER
B23: ⚠️ DISCLAIMER: This template is for educational and informational purposes only.
B24: It does not constitute personalized financial, investment, tax, or legal advice.
B25: Consult a registered financial advisor for advice specific to your situation.
B26: © Her Money & AI | AI-Powered Finance Education | hermoneyandai.ca

Sheet 📅 Timeline
B1: FIRE PROJECTION TIMELINE
B2: Year-by-year portfolio growth — auto-calculated from Progress Tracker
B4: YEAR-BY-YEAR PROJECTION (20 YEARS)
B5: Year | C5: Age | D5: Portfolio Start | E5: Annual Savings | F5: Return Earned | G5: Portfolio End
B6: =YEAR(TODAY())+0 -> 2026 | C6: ='📈 Progress Tracker'!C6+0 -> 0 | D6: ='📈 Progress Tracker'!C10 -> 0 | E6: ='📈 Progress Tracker'!C13 -> 0 | F6: =(D6+E6)*'📈 Progress Tracker'!C14 -> 0 | G6: =D6+E6+F6 -> 0
B7: =B6+1 -> 2027 | C7: ='📈 Progress Tracker'!C6+1 -> 1 | D7: =G6 -> 0 | E7: ='📈 Progress Tracker'!C13 -> 0 | F7: =(D7+E7)*'📈 Progress Tracker'!C14 -> 0 | G7: =D7+E7+F7 -> 0
B8: =B7+1 -> 2028 | C8: ='📈 Progress Tracker'!C6+2 -> 2 | D8: =G7 -> 0 | E8: ='📈 Progress Tracker'!C13 -> 0 | F8: =(D8+E8)*'📈 Progress Tracker'!C14 -> 0 | G8: =D8+E8+F8 -> 0
B9: =B8+1 -> 2029 | C9: ='📈 Progress Tracker'!C6+3 -> 3 | D9: =G8 -> 0 | E9: ='📈 Progress Tracker'!C13 -> 0 | F9: =(D9+E9)*'📈 Progress Tracker'!C14 -> 0 | G9: =D9+E9+F9 -> 0
B10: =B9+1 -> 2030 | C10: ='📈 Progress Tracker'!C6+4 -> 4 | D10: =G9 -> 0 | E10: ='📈 Progress Tracker'!C13 -> 0 | F10: =(D10+E10)*'📈 Progress Tracker'!C14 -> 0 | G10: =D10+E10+F10 -> 0
B11: =B10+1 -> 2031 | C11: ='📈 Progress Tracker'!C6+5 -> 5 | D11: =G10 -> 0 | E11: ='📈 Progress Tracker'!C13 -> 0 | F11: =(D11+E11)*'📈 Progress Tracker'!C14 -> 0 | G11: =D11+E11+F11 -> 0
B12: =B11+1 -> 2032 | C12: ='📈 Progress Tracker'!C6+6 -> 6 | D12: =G11 -> 0 | E12: ='📈 Progress Tracker'!C13 -> 0 | F12: =(D12+E12)*'📈 Progress Tracker'!C14 -> 0 | G12: =D12+E12+F12 -> 0
B13: =B12+1 -> 2033 | C13: ='📈 Progress Tracker'!C6+7 -> 7 | D13: =G12 -> 0 | E13: ='📈 Progress Tracker'!C13 -> 0 | F13: =(D13+E13)*'📈 Progress Tracker'!C14 -> 0 | G13: =D13+E13+F13 -> 0
B14: =B13+1 -> 2034 | C14: ='📈 Progress Tracker'!C6+8 -> 8 | D14: =G13 -> 0 | E14: ='📈 Progress Tracker'!C13 -> 0 | F14: =(D14+E14)*'📈 Progress Tracker'!C14 -> 0 | G14: =D14+E14+F14 -> 0
B15: =B14+1 -> 2035 | C15: ='📈 Progress Tracker'!C6+9 -> 9 | D15: =G14 -> 0 | E15: ='📈 Progress Tracker'!C13 -> 0 | F15: =(D15+E15)*'📈 Progress Tracker'!C14 -> 0 | G15: =D15+E15+F15 -> 0
B16: =B15+1 -> 2036 | C16: ='📈 Progress Tracker'!C6+10 -> 10 | D16: =G15 -> 0 | E16: ='📈 Progress Tracker'!C13 -> 0 | F16: =(D16+E16)*'📈 Progress Tracker'!C14 -> 0 | G16: =D16+E16+F16 -> 0
B17: =B16+1 -> 2037 | C17: ='📈 Progress Tracker'!C6+11 -> 11 | D17: =G16 -> 0 | E17: ='📈 Progress Tracker'!C13 -> 0 | F17: =(D17+E17)*'📈 Progress Tracker'!C14 -> 0 | G17: =D17+E17+F17 -> 0
B18: =B17+1 -> 2038 | C18: ='📈 Progress Tracker'!C6+12 -> 12 | D18: =G17 -> 0 | E18: ='📈 Progress Tracker'!C13 -> 0 | F18: =(D18+E18)*'📈 Progress Tracker'!C14 -> 0 | G18: =D18+E18+F18 -> 0
B19: =B18+1 -> 2039 | C19: ='📈 Progress Tracker'!C6+13 -> 13 | D19: =G18 -> 0 | E19: ='📈 Progress Tracker'!C13 -> 0 | F19: =(D19+E19)*'📈 Progress Tracker'!C14 -> 0 | G19: =D19+E19+F19 -> 0
B20: =B19+1 -> 2040 | C20: ='📈 Progress Tracker'!C6+14 -> 14 | D20: =G19 -> 0 | E20: ='📈 Progress Tracker'!C13 -> 0 | F20: =(D20+E20)*'📈 Progress Tracker'!C14 -> 0 | G20: =D20+E20+F20 -> 0
B21: =B20+1 -> 2041 | C21: ='📈 Progress Tracker'!C6+15 -> 15 | D21: =G20 -> 0 | E21: ='📈 Progress Tracker'!C13 -> 0 | F21: =(D21+E21)*'📈 Progress Tracker'!C14 -> 0 | G21: =D21+E21+F21 -> 0
B22: =B21+1 -> 2042 | C22: ='📈 Progress Tracker'!C6+16 -> 16 | D22: =G21 -> 0 | E22: ='📈 Progress Tracker'!C13 -> 0 | F22: =(D22+E22)*'📈 Progress Tracker'!C14 -> 0 | G22: =D22+E22+F22 -> 0
B23: =B22+1 -> 2043 | C23: ='📈 Progress Tracker'!C6+17 -> 17 | D23: =G22 -> 0 | E23: ='📈 Progress Tracker'!C13 -> 0 | F23: =(D23+E23)*'📈 Progress Tracker'!C14 -> 0 | G23: =D23+E23+F23 -> 0
B24: =B23+1 -> 2044 | C24: ='📈 Progress Tracker'!C6+18 -> 18 | D24: =G23 -> 0 | E24: ='📈 Progress Tracker'!C13 -> 0 | F24: =(D24+E24)*'📈 Progress Tracker'!C14 -> 0 | G24: =D24+E24+F24 -> 0
B25: =B24+1 -> 2045 | C25: ='📈 Progress Tracker'!C6+19 -> 19 | D25: =G24 -> 0 | E25: ='📈 Progress Tracker'!C13 -> 0 | F25: =(D25+E25)*'📈 Progress Tracker'!C14 -> 0 | G25: =D25+E25+F25 -> 0
B28: EDUCATIONAL USE DISCLAIMER
B29: ⚠️ DISCLAIMER: This template is for educational and informational purposes only.
B30: It does not constitute personalized financial, investment, tax, or legal advice.
B31: Consult a registered financial advisor for advice specific to your situation.
B32: © Her Money & AI | AI-Powered Finance Education | hermoneyandai.ca

Sheet 🍁 Canada Tips
B1: CANADIAN FIRE STRATEGY GUIDE
B2: Tax-efficient paths to financial independence in Canada
B4: 🍁 FIRE ACCOUNT ORDER FOR CANADIANS
B5: • Step 1: Emergency fund (3-6 months expenses) in HISA
B6: • Step 2: FHSA if buying a home — tax deduction + tax-free growth
B7: • Step 3: RRSP if your marginal tax rate today > expected rate in retirement
B8: • Step 4: TFSA — tax-free growth and withdrawals, maximum flexibility
B9: • Step 5: Non-registered investing once registered accounts are maxed
B12: 💡 LEAN, REGULAR & FAT FIRE IN CANADA
B13: • Lean FIRE: 20x annual expenses. Frugal lifestyle. Possible in lower cost-of-living cities.
B14: • Regular FIRE: 25x annual expenses (4% SWR). Most popular — works in most Canadian cities.
B15: • Fat FIRE: 30-33x annual expenses. Comfortable retirement with travel and lifestyle spending.
... B30: © Her Money & AI | AI-Powered Finance Education | hermoneyandai.ca
